{
    "championships": 0,
    "code": "MAS",
    "collection_name": "Felipe Massa 🇧🇷",
    "country": "Brazil",
    "country_code": "br",
    "country_flag": "🇧🇷",
    "did_not_finish": 41,
    "did_not_start": 1,
    "dob": "1981-04-25",
    "driverId": 13,
    "driverRef": "massa",
    "fastestlaps": 15,
    "finished_in_points": 156,
    "first_race": "2002-03-03",
    "first_win": "2006-08-27",
    "forename": "Felipe",
    "fullname": "Felipe Massa",
    "last_race": "2017-06-25",
    "last_win": "2008-11-02",
    "participations": 260,
    "permanent_number": 19,
    "podiums": 41,
    "points": 1144.0,
    "poles": 16,
    "races_finished": 218,
    "seasons": 15,
    "subchampionships": 1,
    "surname": "Massa",
    "top_ten": 178,
    "wins": 11
}