{
  "participations" : 17,
  "country" : "Italy",
  "dob" : "1957-01-02T00:00:00.000Z",
  "did_not_start" : 14,
  "last_win" : null,
  "podiums" : 0,
  "last_race" : "1981-10-17T00:00:00.000Z",
  "permanent_number" : null,
  "championships" : 0,
  "country_flag" : "🇮🇹",
  "surname" : "Gabbiani",
  "country_code" : "it",
  "code" : null,
  "top_ten" : 0,
  "fullname" : "Beppe Gabbiani",
  "did_not_finish" : 3,
  "first_win" : null,
  "fastestlaps" : 0,
  "races_finished" : 0,
  "first_race" : "1978-10-01T00:00:00.000Z",
  "driverRef" : "gabbiani",
  "poles" : 0,
  "seasons" : 2,
  "subchampionships" : 0,
  "driverId" : 213,
  "wins" : 0,
  "forename" : "Beppe",
  "collection_name" : "Beppe Gabbiani 🇮🇹",
  "finished_in_points" : 0,
  "points" : 0
}