{
  "participations" : 4,
  "country" : "Italy",
  "dob" : "1941-08-30T00:00:00.000Z",
  "did_not_start" : 0,
  "last_win" : null,
  "podiums" : 0,
  "last_race" : "1970-09-06T00:00:00.000Z",
  "permanent_number" : null,
  "championships" : 0,
  "country_flag" : "🇮🇹",
  "surname" : "Giunti",
  "country_code" : "it",
  "code" : null,
  "top_ten" : 2,
  "fullname" : "Ignazio Giunti",
  "did_not_finish" : 1,
  "first_win" : null,
  "fastestlaps" : 0,
  "races_finished" : 3,
  "first_race" : "1970-06-07T00:00:00.000Z",
  "driverRef" : "giunti",
  "poles" : 0,
  "seasons" : 1,
  "subchampionships" : 0,
  "driverId" : 363,
  "wins" : 0,
  "forename" : "Ignazio",
  "collection_name" : "Ignazio Giunti 🇮🇹",
  "finished_in_points" : 1,
  "points" : 3
}